MANIFEST.in
README.md
requirements.txt
setup.cfg
setup.py
vsdcli/__init__.py
vsdcli/commands.py
vsdcli/printer.py
vsdcli/utils.py
vsdcli/vsd.py
vsdcli.egg-info/PKG-INFO
vsdcli.egg-info/SOURCES.txt
vsdcli.egg-info/dependency_links.txt
vsdcli.egg-info/entry_points.txt
vsdcli.egg-info/requires.txt
vsdcli.egg-info/top_level.txt