Metadata-Version: 1.0
Name: vsdcli
Version: 3.2.4.134
Summary: VSD Command Line Interface
Home-page: https://github.com/nuagenetworks
Author: Christophe Serafin
Author-email: christophe.serafin@nuagenetworks.net
License: BSD-3
Platform: UNKNOWN
Classifier: Development Status :: 5 - Production/Stable
Classifier: Topic :: Utilities
Classifier: License :: OSI Approved :: BSD License
Classifier: Environment :: Console
Classifier: Intended Audience :: Developers
